cloudpub_python_sdk-2.4.5.dist-info/METADATA
cloudpub_python_sdk-2.4.5.dist-info/WHEEL
cloudpub_python_sdk/__init__.py
cloudpub_python_sdk/cloudpub_python_sdk.abi3.so
cloudpub_python_sdk-2.4.5.dist-info/RECORD
