Metadata-Version: 2.4
Name: cloudpub_python_sdk
Version: 2.4.5
Classifier: Programming Language :: Python
Classifier: Programming Language :: Python :: 3
Classifier: Programming Language :: Python :: 3.8
Classifier: Programming Language :: Python :: 3.9
Classifier: Programming Language :: Python :: 3.10
Classifier: Programming Language :: Python :: 3.11
Classifier: Programming Language :: Python :: 3.12
Classifier: Programming Language :: Python :: 3.13
Classifier: Programming Language :: Python :: 3.14
Classifier: Programming Language :: Rust
Classifier: Operating System :: OS Independent
Classifier: Development Status :: 4 - Beta
Summary: Python bindings for CloudPub client
Home-Page: https://github.com/ermak-dev/cloudpub
Requires-Python: >=3.8
